ocelot/__init__.py
ocelot/calculate/__init__.py
ocelot/calculate/calculate.py
ocelot/calculate/distance.py
ocelot/calculate/generic.py
ocelot/calculate/motion.py
ocelot/calculate/position.py
ocelot/cluster/__init__.py
ocelot/cluster/epsilon.py
ocelot/cluster/nearest_neighbor.py
ocelot/cluster/preprocess.py
ocelot/cluster/resample.py
ocelot/crossmatch/__init__.py
ocelot/crossmatch/_catalogue.py
ocelot/isochrone/__init__.py
ocelot/isochrone/interpolate.py
ocelot/isochrone/io.py
ocelot/model/__init__.py
ocelot/model/binaries/__init__.py
ocelot/model/binaries/_base.py
ocelot/model/binaries/moe_distefano_17.py
ocelot/model/differential_reddening/__init__.py
ocelot/model/differential_reddening/_base.py
ocelot/model/differential_reddening/differential_reddening.py
ocelot/model/distribution/__init__.py
ocelot/model/distribution/_base.py
ocelot/model/distribution/king62.py
ocelot/model/distribution/king64.py
ocelot/model/distribution/plummer.py
ocelot/model/observation/__init__.py
ocelot/model/observation/_base.py
ocelot/model/observation/common.py
ocelot/model/observation/subsample_selection.py
ocelot/model/observation/gaia/__init__.py
ocelot/model/observation/gaia/gaia_dr3.py
ocelot/model/observation/gaia/photutils.py
ocelot/plot/__init__.py
ocelot/plot/gaia_explorer.py
ocelot/plot/plot_figure.py
ocelot/plot/process.py
ocelot/plot/utilities.py
ocelot/plot/axis/__init__.py
ocelot/plot/axis/cluster.py
ocelot/plot/axis/nn_statistics.py
ocelot/simulate/__init__.py
ocelot/simulate/astrometry.py
ocelot/simulate/binaries.py
ocelot/simulate/cluster.py
ocelot/simulate/errors.py
ocelot/simulate/observation.py
ocelot/simulate/photometry.py
ocelot/simulate/uncertainties.py
ocelot/util/__init__.py
ocelot/util/check.py
ocelot/util/coordinates.py
ocelot/util/magnitudes.py
ocelot/util/random.py
ocelot/util/stats.py
ocelot/verify/__init__.py
ocelot/verify/find.py
ocelot/verify/significance.py
ocelot/verify/stats.py
ocelot-0.4.8.dist-info/licenses/LICENSE
ocelot-0.4.8.dist-info/METADATA
ocelot-0.4.8.dist-info/WHEEL
ocelot-0.4.8.dist-info/top_level.txt
ocelot-0.4.8.dist-info/RECORD
