Metadata-Version: 2.4
Name: ocelot
Version: 0.4.8
Summary: A toolbox for working with observations of star clusters.
Author-email: Emily Hunt <emily.hunt.physics@gmail.com>
Maintainer-email: Emily Hunt <emily.hunt.physics@gmail.com>
License: MIT License
Project-URL: Homepage, https://ocelot-docs.org
Project-URL: Bug Reports, https://github.com/emilyhunt/ocelot/issues
Project-URL: Source, https://github.com/emilyhunt/ocelot
Keywords: astronomy,star cluster,threading,development
Classifier: Development Status :: 3 - Alpha
Classifier: Intended Audience :: Developers
Classifier: License :: OSI Approved :: MIT License
Classifier: Programming Language :: Python :: 3
Classifier: Programming Language :: Python :: 3.10
Classifier: Programming Language :: Python :: 3.11
Classifier: Programming Language :: Python :: 3.12
Classifier: Programming Language :: Python :: 3 :: Only
Requires-Python: >=3.10
License-File: LICENSE
Requires-Dist: numpy<3.0,>1.21.0
Requires-Dist: numba>=0.50
Requires-Dist: matplotlib<4.0,>3.4.0
Requires-Dist: scikit-learn<2.0,>0.24.0
Requires-Dist: scipy<2.0,>1.0.0
Requires-Dist: pandas<3.0,>1.0.0
Requires-Dist: pyarrow
Requires-Dist: astropy>=6.0.0
Requires-Dist: healpy<2.0,>1.13.0
Requires-Dist: galpy<2.0,>1.9
Requires-Dist: dustmaps
Requires-Dist: gaiaunlimited
Requires-Dist: kepler.py
Requires-Dist: initial_mass_function==2025.1.20
Provides-Extra: dev
Requires-Dist: mkdocs-material[imaging]; extra == "dev"
Requires-Dist: mkdocstrings[python]>=0.18; extra == "dev"
Requires-Dist: mkdocs-jupyter; extra == "dev"
Requires-Dist: jupyter; extra == "dev"
Requires-Dist: check-manifest; extra == "dev"
Requires-Dist: pytest; extra == "dev"
Requires-Dist: ruff; extra == "dev"
Provides-Extra: docs
Requires-Dist: mkdocs-material[imaging]; extra == "docs"
Requires-Dist: mkdocstrings[python]>=0.18; extra == "docs"
Requires-Dist: mkdocs-jupyter; extra == "docs"
Provides-Extra: test
Requires-Dist: pytest; extra == "test"
Dynamic: license-file
